osmxmpp/__init__.py
osmxmpp/ci.py
osmxmpp/client.py
osmxmpp/message.py
osmxmpp/permission.py
osmxmpp/validation.py
osmxmpp/extensions/__init__.py
osmxmpp/extensions/abc.py
osmxmpp/extensions/omemo/__init__.py
osmxmpp/extensions/omemo/base.py
osmxmpp/extensions/omemo/xml.py
osmxmpp/extensions/roster/__init__.py
osmxmpp/extensions/roster/subscription/__init__.py
osmxmpp/extensions/roster/subscription/base.py
osmxmpp/extensions/roster/subscription/xml.py
osmxmpp/extensions/service/__init__.py
osmxmpp/extensions/service/discovery/__init__.py
osmxmpp/extensions/service/discovery/base.py
osmxmpp/extensions/service/discovery/xml.py
osmxmpp/features/__init__.py
osmxmpp/features/abc.py
osmxmpp/features/bind.py
osmxmpp/features/sasl.py
osmxmpp/features/tls.py
osmxmpp-1.0.1.dist-info/METADATA
osmxmpp-1.0.1.dist-info/WHEEL
osmxmpp-1.0.1.dist-info/top_level.txt
osmxmpp-1.0.1.dist-info/RECORD
