Metadata-Version: 2.4
Name: osmxmpp
Version: 1.0.1
Summary: Python XMPP library
Author: osmiumnet
Project-URL: Documentation, https://osmxmpp.readthedocs.io/en/latest/
Project-URL: Source, https://github.com/osmiumnet/osmxmpp
Requires-Python: >=3.10
Requires-Dist: osmxml==1.0.1
Requires-Dist: osmomemo==1.1.2
Dynamic: author
Dynamic: requires-python
